tinyfk/__init__.py
tinyfk/_tinyfk.cpython-38-x86_64-linux-gnu.so
tinyfk/py.typed
tinyfk-0.6.7.dist-info/LICENSE
tinyfk-0.6.7.dist-info/METADATA
tinyfk-0.6.7.dist-info/WHEEL
tinyfk-0.6.7.dist-info/top_level.txt
tinyfk-0.6.7.dist-info/RECORD
