Metadata-Version: 2.1
Name: tinyfk
Version: 0.6.7
Summary: a fast kinematics solver
Home-page: UNKNOWN
Author: Hirokazu Ishida
Author-email: UNKNOWN
License: MIT
Platform: UNKNOWN
